kabelwerk/__init__.py
kabelwerk/apps.py
kabelwerk/config.py
kabelwerk/exceptions.py
kabelwerk/models.py
kabelwerk/utils.py
kabelwerk/api/__init__.py
kabelwerk/api/base.py
kabelwerk/api/rooms.py
kabelwerk/api/users.py
kabelwerk-0.1.2.dist-info/LICENSE
kabelwerk-0.1.2.dist-info/WHEEL
kabelwerk-0.1.2.dist-info/METADATA
kabelwerk-0.1.2.dist-info/RECORD
