Metadata-Version: 2.1
Name: kabelwerk
Version: 0.1.2
Summary: The Kabelwerk SDK for Python.
Keywords: kabelwerk
Author-email: Kabelwerk <devs@kabelwerk.io>
Classifier: Development Status :: 3 - Alpha
Classifier: Intended Audience :: Developers
Classifier: License :: OSI Approved :: MIT License
Classifier: Programming Language :: Python :: 3
Classifier: Topic :: Communications :: Chat
Classifier: Topic :: Internet :: WWW/HTTP
Requires-Dist: requests >= 2.31
Requires-Dist: flit ; extra == "dev"
Requires-Dist: pip-tools ; extra == "dev"
Requires-Dist: pytest ; extra == "dev"
Requires-Dist: responses ; extra == "dev"
Requires-Dist: sphinx ; extra == "dev"
Requires-Dist: sphinx_rtd_theme ; extra == "dev"
Project-URL: Changelog, https://github.com/kabelwerk/sdk-python/blob/master/CHANGELOG.rst
Project-URL: Documentation, https://docs.kabelwerk.io/python/
Project-URL: Home, https://kabelwerk.io
Project-URL: Source, https://github.com/kabelwerk/sdk-python
Project-URL: Tracker, https://github.com/kabelwerk/sdk-python/issues
Provides-Extra: dev
